{
  "version": "7",
  "dialect": "postgresql",
  "entries": [
    {
      "idx": 0,
      "version": "7",
      "when": 1725930109768,
      "tag": "0000_supreme_wildside",
      "breakpoints": true
    },
    {
      "idx": 1,
      "version": "7",
      "when": 1725930495036,
      "tag": "0001_bouncy_blue_shield",
      "breakpoints": true
    },
    {
      "idx": 2,
      "version": "7",
      "when": 1726875012711,
      "tag": "0002_melodic_boomer",
      "breakpoints": true
    },
    {
      "idx": 3,
      "version": "7",
      "when": 1727392922755,
      "tag": "0003_slim_kree",
      "breakpoints": true
    }
  ]
}